libanoncai/__init__.py
libanoncai/core.py
libanoncai/types.py
libanoncai-1.0.0.dist-info/licenses/LICENSE
libanoncai-1.0.0.dist-info/METADATA
libanoncai-1.0.0.dist-info/WHEEL
libanoncai-1.0.0.dist-info/top_level.txt
libanoncai-1.0.0.dist-info/RECORD
