Metadata-Version: 2.4
Name: libanoncai
Version: 1.0.0
Summary: Libanoncai
Author-email: piopysp <admin@mail.roominator.xyz>
License-Expression: MIT
Project-URL: Homepage, https://github.com/RoominatorAI/libanoncai
Project-URL: Issues, https://github.com/RoominatorAI/libanoncai/issues
Classifier: Programming Language :: Python :: 3
Classifier: Operating System :: OS Independent
Requires-Python: >=3.8
License-File: LICENSE
Requires-Dist: requests
Requires-Dist: aiohttp
Requires-Dist: PyCharacterAI
Dynamic: license-file
